{
  "backtest": {
    "base_dir": "backtests",
    "combine_ohlcvs": true,
    "compress_cache": true,
    "end_date": "2025-03-08",
    "exchanges": [
      "bybit"
    ],
    "gap_tolerance_ohlcvs_minutes": 120,
    "start_date": "2025-02-06",
    "starting_balance": 10000
  },
  "bot": {
    "long": {
      "close_grid_markup_range": 0.0135033087144691,
      "close_grid_min_markup": 0.004979062396751137,
      "close_grid_qty_pct": 0.7499977097322053,
      "close_trailing_grid_ratio": 0,
      "close_trailing_qty_pct": 0,
      "close_trailing_retracement_pct": 0,
      "close_trailing_threshold_pct": 0,
      "ema_span_0": 334.3021342724357,
      "ema_span_1": 205.11153059903532,
      "enforce_exposure_limit": true,
      "entry_grid_double_down_factor": 2.2291620079027763,
      "entry_grid_spacing_pct": 0.0056061682440994584,
      "entry_grid_spacing_weight": 0.6776785325217772,
      "entry_initial_ema_dist": -0.09347349459796278,
      "entry_initial_qty_pct": 0.04775689973868951,
      "entry_trailing_grid_ratio": -0.5000022148703374,
      "entry_trailing_retracement_pct": 0.018918656963396317,
      "entry_trailing_threshold_pct": 0.047859142592267756,
      "filter_relative_volume_clip_pct": 0.506719461668353,
      "filter_rolling_window": 273.90831433382243,
      "n_positions": 3.9833908002673204,
      "total_wallet_exposure_limit": 0.6167417126456123,
      "unstuck_close_pct": 0.07860130130199552,
      "unstuck_ema_dist": 0.0035525248431620368,
      "unstuck_loss_allowance_pct": 0.03909627414146347,
      "unstuck_threshold": 0.9219155995578262
    },
    "short": {
      "close_grid_markup_range": 0.014301230003649305,
      "close_grid_min_markup": 0.004923937456599861,
      "close_grid_qty_pct": 0.5728982673170088,
      "close_trailing_grid_ratio": -0.25001821780822986,
      "close_trailing_qty_pct": 0.6229111063098727,
      "close_trailing_retracement_pct": 0.005555813302078987,
      "close_trailing_threshold_pct": 0.040971925707449106,
      "ema_span_0": 776.2521294060117,
      "ema_span_1": 925.4138489153404,
      "enforce_exposure_limit": true,
      "entry_grid_double_down_factor": 2.0000087618045335,
      "entry_grid_spacing_pct": 0.014998720589875482,
      "entry_grid_spacing_weight": 4.598562867929371,
      "entry_initial_ema_dist": 0.0029729599339388857,
      "entry_initial_qty_pct": 0.035308243614458355,
      "entry_trailing_grid_ratio": -0.7499996259076723,
      "entry_trailing_retracement_pct": 0.01482856341314446,
      "entry_trailing_threshold_pct": 0.04507820084827064,
      "filter_relative_volume_clip_pct": 0.06955333231883355,
      "filter_rolling_window": 336.8149289523954,
      "n_positions": 3.571544878340427,
      "total_wallet_exposure_limit": 0.7037560836939578,
      "unstuck_close_pct": 0.0030204012315600405,
      "unstuck_ema_dist": 0.0022207287314443963,
      "unstuck_loss_allowance_pct": 0.003751303642137181,
      "unstuck_threshold": 0.9488690076880466
    }
  },
  "live": {
    "approved_coins": [
      "ADA"
    ],
    "auto_gs": true,
    "coin_flags": {},
    "empty_means_all_approved": true,
    "execution_delay_seconds": 2,
    "filter_by_min_effective_cost": true,
    "forced_mode_long": "",
    "forced_mode_short": "",
    "ignored_coins": {
      "long": [],
      "short": []
    },
    "leverage": 10,
    "market_orders_allowed": true,
    "max_n_cancellations_per_batch": 5,
    "max_n_creations_per_batch": 3,
    "max_n_restarts_per_day": 10,
    "minimum_coin_age_days": 30,
    "ohlcvs_1m_rolling_window_days": 4,
    "ohlcvs_1m_update_after_minutes": 10,
    "pnls_max_lookback_days": 30,
    "price_distance_threshold": 0.002,
    "time_in_force": "good_till_cancelled",
    "user": "bybit_passivbot"
  },
  "optimize": {
    "bounds": {
      "long_close_grid_markup_range": [
        0.005,
        0.015
      ],
      "long_close_grid_min_markup": [
        0.001,
        0.005
      ],
      "long_close_grid_qty_pct": [
        0.5,
        0.75
      ],
      "long_close_trailing_grid_ratio": [
        0,
        0
      ],
      "long_close_trailing_qty_pct": [
        0,
        0
      ],
      "long_close_trailing_retracement_pct": [
        0,
        0
      ],
      "long_close_trailing_threshold_pct": [
        0,
        0
      ],
      "long_ema_span_0": [
        200,
        1440
      ],
      "long_ema_span_1": [
        200,
        1440
      ],
      "long_entry_grid_double_down_factor": [
        2,
        3
      ],
      "long_entry_grid_spacing_pct": [
        0.005,
        0.015
      ],
      "long_entry_grid_spacing_weight": [
        0,
        5
      ],
      "long_entry_initial_ema_dist": [
        -0.1,
        0.003
      ],
      "long_entry_initial_qty_pct": [
        0.025,
        0.05
      ],
      "long_entry_trailing_grid_ratio": [
        -0.75,
        -0.5
      ],
      "long_entry_trailing_retracement_pct": [
        0.005,
        0.02
      ],
      "long_entry_trailing_threshold_pct": [
        0.02,
        0.05
      ],
      "long_filter_relative_volume_clip_pct": [
        0.506719461668353,
        0.506719461668353
      ],
      "long_filter_rolling_window": [
        273.90831433382243,
        273.90831433382243
      ],
      "long_n_positions": [
        3.9833908002673204,
        3.9833908002673204
      ],
      "long_total_wallet_exposure_limit": [
        0.6167417126456123,
        0.6167417126456123
      ],
      "long_unstuck_close_pct": [
        0.07860130130199552,
        0.07860130130199552
      ],
      "long_unstuck_ema_dist": [
        -0.1,
        0.01
      ],
      "long_unstuck_loss_allowance_pct": [
        0.03909627414146347,
        0.03909627414146347
      ],
      "long_unstuck_threshold": [
        0.75,
        0.95
      ],
      "short_close_grid_markup_range": [
        0.005,
        0.015
      ],
      "short_close_grid_min_markup": [
        0.001,
        0.005
      ],
      "short_close_grid_qty_pct": [
        0.5,
        0.75
      ],
      "short_close_trailing_grid_ratio": [
        -0.5,
        -0.25
      ],
      "short_close_trailing_qty_pct": [
        0.5,
        0.75
      ],
      "short_close_trailing_retracement_pct": [
        0.005,
        0.02
      ],
      "short_close_trailing_threshold_pct": [
        0.02,
        0.05
      ],
      "short_ema_span_0": [
        200,
        1440
      ],
      "short_ema_span_1": [
        200,
        1440
      ],
      "short_entry_grid_double_down_factor": [
        2,
        3
      ],
      "short_entry_grid_spacing_pct": [
        0.005,
        0.015
      ],
      "short_entry_grid_spacing_weight": [
        0,
        5
      ],
      "short_entry_initial_ema_dist": [
        -0.1,
        0.003
      ],
      "short_entry_initial_qty_pct": [
        0.025,
        0.05
      ],
      "short_entry_trailing_grid_ratio": [
        -0.75,
        -0.5
      ],
      "short_entry_trailing_retracement_pct": [
        0.005,
        0.02
      ],
      "short_entry_trailing_threshold_pct": [
        0.02,
        0.05
      ],
      "short_filter_relative_volume_clip_pct": [
        0.06955333231883355,
        0.06955333231883355
      ],
      "short_filter_rolling_window": [
        336.8149289523954,
        336.8149289523954
      ],
      "short_n_positions": [
        3.571544878340427,
        3.571544878340427
      ],
      "short_total_wallet_exposure_limit": [
        0.7037560836939578,
        0.7037560836939578
      ],
      "short_unstuck_close_pct": [
        0.0030204012315600405,
        0.0030204012315600405
      ],
      "short_unstuck_ema_dist": [
        -0.1,
        0.01
      ],
      "short_unstuck_loss_allowance_pct": [
        0.003751303642137181,
        0.003751303642137181
      ],
      "short_unstuck_threshold": [
        0.75,
        0.95
      ]
    },
    "compress_results_file": true,
    "crossover_probability": 0.7,
    "iters": 300000,
    "limits": {
      "lower_bound_drawdown_worst": 0.333,
      "lower_bound_drawdown_worst_mean_1pct": 0.1,
      "lower_bound_equity_balance_diff_neg_max": 0.4,
      "lower_bound_equity_balance_diff_neg_mean": 0.01,
      "lower_bound_equity_balance_diff_pos_max": 0.5,
      "lower_bound_equity_balance_diff_pos_mean": 0.02,
      "lower_bound_loss_profit_ratio": 0.5
    },
    "mutation_probability": 0.2,
    "n_cpus": 10,
    "population_size": 500,
    "scoring": [
      "mdg",
      "sterling_ratio"
    ]
  }
}